slowedvideos/__init__.py
slowedvideos/audio.py
slowedvideos/extras.py
slowedvideos/gui.py
slowedvideos/video.py
slowedvideos/fonts/__init__.py
slowedvideos/fonts/down1_font.ttf
slowedvideos/fonts/down2_font.ttf
slowedvideos/fonts/toptext_font.ttf
slowedvideos/vst/__init__.py
slowedvideos/vst/TAL-Reverb-4.vst3/Contents/x86_64-linux/TAL-Reverb-4.so
slowedvideos-0.4.5.dist-info/LICENSE
slowedvideos-0.4.5.dist-info/METADATA
slowedvideos-0.4.5.dist-info/WHEEL
slowedvideos-0.4.5.dist-info/top_level.txt
slowedvideos-0.4.5.dist-info/RECORD
