Metadata-Version: 2.1
Name: slowedvideos
Version: 0.4.5
Summary: Various scripts from justcow.
Home-page: UNKNOWN
Author: JustCow
Author-email: <justcow@pm.me>
License: UNKNOWN
Keywords: python,video,audio,justcow
Platform: UNKNOWN
Classifier: Programming Language :: Python :: 3
Classifier: Operating System :: Unix
Classifier: Operating System :: MacOS :: MacOS X
Classifier: Operating System :: Microsoft :: Windows
License-File: LICENSE
Requires-Dist: moviepy
Requires-Dist: pydub
Requires-Dist: pedalboard
Requires-Dist: yt-dlp
Requires-Dist: pillow
Requires-Dist: soundfile
Requires-Dist: requests
